odoo10_addon_website_sale_category_alphabetic-10.0.1.0.0.99.dev3-py3.8-nspkg.pth
odoo/addons/website_sale_category_alphabetic/README.rst
odoo/addons/website_sale_category_alphabetic/__init__.py
odoo/addons/website_sale_category_alphabetic/__manifest__.py
odoo/addons/website_sale_category_alphabetic/hooks.py
odoo/addons/website_sale_category_alphabetic/data/product_public_category.xml
odoo/addons/website_sale_category_alphabetic/demo/product_public_category.xml
odoo/addons/website_sale_category_alphabetic/demo/product_template.xml
odoo/addons/website_sale_category_alphabetic/i18n/ca.po
odoo/addons/website_sale_category_alphabetic/i18n/de.po
odoo/addons/website_sale_category_alphabetic/i18n/es.po
odoo/addons/website_sale_category_alphabetic/i18n/es_MX.po
odoo/addons/website_sale_category_alphabetic/i18n/fi.po
odoo/addons/website_sale_category_alphabetic/i18n/fr.po
odoo/addons/website_sale_category_alphabetic/i18n/fr_CH.po
odoo/addons/website_sale_category_alphabetic/i18n/hr.po
odoo/addons/website_sale_category_alphabetic/i18n/hr_HR.po
odoo/addons/website_sale_category_alphabetic/i18n/it.po
odoo/addons/website_sale_category_alphabetic/i18n/nl_NL.po
odoo/addons/website_sale_category_alphabetic/i18n/pt_BR.po
odoo/addons/website_sale_category_alphabetic/i18n/ro.po
odoo/addons/website_sale_category_alphabetic/i18n/sl.po
odoo/addons/website_sale_category_alphabetic/i18n/tr_TR.po
odoo/addons/website_sale_category_alphabetic/i18n/vi_VN.po
odoo/addons/website_sale_category_alphabetic/i18n/website_sale_category_alphabetic.pot
odoo/addons/website_sale_category_alphabetic/i18n/zh_CN.po
odoo/addons/website_sale_category_alphabetic/models/__init__.py
odoo/addons/website_sale_category_alphabetic/models/product_template.py
odoo/addons/website_sale_category_alphabetic/static/description/icon.png
odoo/addons/website_sale_category_alphabetic/tests/__init__.py
odoo/addons/website_sale_category_alphabetic/tests/test_hooks.py
odoo10_addon_website_sale_category_alphabetic-10.0.1.0.0.99.dev3.dist-info/METADATA
odoo10_addon_website_sale_category_alphabetic-10.0.1.0.0.99.dev3.dist-info/WHEEL
odoo10_addon_website_sale_category_alphabetic-10.0.1.0.0.99.dev3.dist-info/namespace_packages.txt
odoo10_addon_website_sale_category_alphabetic-10.0.1.0.0.99.dev3.dist-info/top_level.txt
odoo10_addon_website_sale_category_alphabetic-10.0.1.0.0.99.dev3.dist-info/RECORD
